README.md
setup.py
json_direct/__init__.py
json_direct.egg-info/PKG-INFO
json_direct.egg-info/SOURCES.txt
json_direct.egg-info/dependency_links.txt
json_direct.egg-info/top_level.txt