Metadata-Version: 2.1
Name: json-direct
Version: 1.0.1
Summary: Overwrite the default behavior of json.dumps to ensure_ascii=False
Home-page: https://github.com/jtc1246/json-direct
Author: Tiancheng Jiao
Author-email: jtc1246@outlook.com
License: MIT
Platform: all
Requires-Python: >=3.6
